{
  "m_GameObject": {
    "m_FileID": 0,
    "m_PathID": 0
  },
  "m_Enabled": 1,
  "m_Script": {
    "m_FileID": 0,
    "m_PathID": 8302033850027404168
  },
  "m_Name": "bu224_ne_SkeletonData",
  "atlasAssets": [
    {
      "m_FileID": 0,
      "m_PathID": 7527001328472241289
    }
  ],
  "scale": 0.01,
  "skeletonJSON": {
    "m_FileID": 0,
    "m_PathID": -2573028176479507129
  },
  "skeletonDataModifiers": [],
  "fromAnimation": [],
  "toAnimation": [],
  "duration": [],
  "defaultMix": 0.2,
  "controller": {
    "m_FileID": 0,
    "m_PathID": 0
  }
}